MANIFEST.in
README
setup.py
reteach/__init__.py
reteach/bb9_course.py
reteach/main.py
reteach/moodle.xml.template
reteach/test_course.py
reteach/utils.py
reteach.egg-info/PKG-INFO
reteach.egg-info/SOURCES.txt
reteach.egg-info/dependency_links.txt
reteach.egg-info/entry_points.txt
reteach.egg-info/not-zip-safe
reteach.egg-info/requires.txt
reteach.egg-info/top_level.txt