Metadata-Version: 1.0
Name: reteach
Version: 1.0.0
Summary: Convert Blackboard (TM) 9 courses into Moodle 1.9 courses
Home-page: http://reteach.org/
Author: Adam Zapletal
Author-email: adamzap@gmail.com
License: GPL v3
Keywords: blackboard,moodle,convert,lms
Platform: any
Classifier: Programming Language :: Python
Classifier: Programming Language :: Python :: 2.5
Classifier: Programming Language :: Python :: 2.6
Classifier: Programming Language :: Python :: 2.7
Classifier: Operating System :: OS Independent
Classifier: License :: OSI Approved :: GNU General Public License (GPL)
